<annotation>
	<folder> strawberry leaf	</folder>
	<filename>102_0829.JPG.jpg</filename>
	<path>/media/master/Data/Sem6/ISDl/Pratik/ strawberry leaf	/102_0829.JPG.jpg</path>
	<source>
		<database>Unknown</database>
	</source>
	<size>
		<width>1600</width>
		<height>1081</height>
		<depth>3</depth>
	</size>
	<segmented>0</segmented>
	<object>
		<name>Strawberry leaf</name>
		<pose>Unspecified</pose>
		<truncated>0</truncated>
		<difficult>0</difficult>
		<bndbox>
			<xmin>710</xmin>
			<ymin>501</ymin>
			<xmax>1170</xmax>
			<ymax>827</ymax>
		</bndbox>
	</object>
	<object>
		<name>Strawberry leaf</name>
		<pose>Unspecified</pose>
		<truncated>0</truncated>
		<difficult>0</difficult>
		<bndbox>
			<xmin>216</xmin>
			<ymin>394</ymin>
			<xmax>615</xmax>
			<ymax>1019</ymax>
		</bndbox>
	</object>
	<object>
		<name>Strawberry leaf</name>
		<pose>Unspecified</pose>
		<truncated>1</truncated>
		<difficult>0</difficult>
		<bndbox>
			<xmin>1</xmin>
			<ymin>201</ymin>
			<xmax>493</xmax>
			<ymax>554</ymax>
		</bndbox>
	</object>
	<object>
		<name>Strawberry leaf</name>
		<pose>Unspecified</pose>
		<truncated>0</truncated>
		<difficult>0</difficult>
		<bndbox>
			<xmin>505</xmin>
			<ymin>81</ymin>
			<xmax>801</xmax>
			<ymax>459</ymax>
		</bndbox>
	</object>
</annotation>
