<annotation>
	<folder> Potato leaf early blight	</folder>
	<filename>20100816earlyblight.jpg</filename>
	<path>/media/master/Data/Sem6/ISDl/Pratik/ Potato leaf early blight	/20100816earlyblight.jpg</path>
	<source>
		<database>Unknown</database>
	</source>
	<size>
		<width>300</width>
		<height>400</height>
		<depth>3</depth>
	</size>
	<segmented>0</segmented>
	<object>
		<name>Potato leaf early blight</name>
		<pose>Unspecified</pose>
		<truncated>0</truncated>
		<difficult>0</difficult>
		<bndbox>
			<xmin>79</xmin>
			<ymin>46</ymin>
			<xmax>231</xmax>
			<ymax>395</ymax>
		</bndbox>
	</object>
</annotation>
