<annotation>
    <folder> Tomato Septoria leaf spot  </folder>
    <filename>2014-08-27%2B-%2BCloser%2BView%2Bof%2BSeptoria%2BLeaf%2BSpot.jpg</filename>
    <size>
        <width>1380</width>
        <height>1600</height>
        <depth>3</depth>
    </size>
    <segmented>0</segmented>
    <object>
        <name>Tomato Septoria leaf spot</name>
        <pose>Unspecified</pose>
        <truncated>0</truncated>
        <occluded>0</occluded>
        <difficult>0</difficult>
        <bndbox>
            <xmin>349</xmin>
            <ymin>884</ymin>
            <xmax>572</xmax>
            <ymax>1128</ymax>
        </bndbox>
    </object>
    <object>
        <name>Tomato Septoria leaf spot</name>
        <pose>Unspecified</pose>
        <truncated>0</truncated>
        <occluded>0</occluded>
        <difficult>0</difficult>
        <bndbox>
            <xmin>1</xmin>
            <ymin>1057</ymin>
            <xmax>410</xmax>
            <ymax>1447</ymax>
        </bndbox>
    </object>
    <object>
        <name>Tomato Septoria leaf spot</name>
        <pose>Unspecified</pose>
        <truncated>0</truncated>
        <occluded>0</occluded>
        <difficult>0</difficult>
        <bndbox>
            <xmin>883</xmin>
            <ymin>898</ymin>
            <xmax>1335</xmax>
            <ymax>1274</ymax>
        </bndbox>
    </object>
    <object>
        <name>Tomato Septoria leaf spot</name>
        <pose>Unspecified</pose>
        <truncated>0</truncated>
        <occluded>0</occluded>
        <difficult>0</difficult>
        <bndbox>
            <xmin>652</xmin>
            <ymin>727</ymin>
            <xmax>901</xmax>
            <ymax>867</ymax>
        </bndbox>
    </object>
    <object>
        <name>Tomato Septoria leaf spot</name>
        <pose>Unspecified</pose>
        <truncated>0</truncated>
        <occluded>0</occluded>
        <difficult>0</difficult>
        <bndbox>
            <xmin>696</xmin>
            <ymin>846</ymin>
            <xmax>870</xmax>
            <ymax>1061</ymax>
        </bndbox>
    </object>
    <object>
        <name>Tomato Septoria leaf spot</name>
        <pose>Unspecified</pose>
        <truncated>0</truncated>
        <occluded>0</occluded>
        <difficult>0</difficult>
        <bndbox>
            <xmin>344</xmin>
            <ymin>782</ymin>
            <xmax>552</xmax>
            <ymax>966</ymax>
        </bndbox>
    </object>
</annotation>