<annotation>
	<folder> Potato leaf late blight	</folder>
	<filename>6a00d8341c4fe353ef011571354632970c-800wi.jpg</filename>
	<path>/media/master/Data/Sem6/ISDl/Pratik/ Potato leaf late blight	/6a00d8341c4fe353ef011571354632970c-800wi.jpg</path>
	<source>
		<database>Unknown</database>
	</source>
	<size>
		<width>800</width>
		<height>600</height>
		<depth>3</depth>
	</size>
	<segmented>0</segmented>
	<object>
		<name>Potato leaf late blight</name>
		<pose>Unspecified</pose>
		<truncated>0</truncated>
		<difficult>0</difficult>
		<bndbox>
			<xmin>445</xmin>
			<ymin>63</ymin>
			<xmax>631</xmax>
			<ymax>280</ymax>
		</bndbox>
	</object>
	<object>
		<name>Potato leaf late blight</name>
		<pose>Unspecified</pose>
		<truncated>0</truncated>
		<difficult>0</difficult>
		<bndbox>
			<xmin>456</xmin>
			<ymin>180</ymin>
			<xmax>754</xmax>
			<ymax>435</ymax>
		</bndbox>
	</object>
	<object>
		<name>Potato leaf late blight</name>
		<pose>Unspecified</pose>
		<truncated>0</truncated>
		<difficult>0</difficult>
		<bndbox>
			<xmin>291</xmin>
			<ymin>48</ymin>
			<xmax>484</xmax>
			<ymax>356</ymax>
		</bndbox>
	</object>
</annotation>
