<annotation>
    <folder> tomato leaf yellow virus </folder>
    <filename>tomato-yellow-closeup-3.jpg</filename>
    <size>
        <width>500</width>
        <height>375</height>
        <depth>3</depth>
    </size>
    <segmented>0</segmented>
    <object>
        <name>Tomato leaf yellow virus</name>
        <pose>Unspecified</pose>
        <truncated>0</truncated>
        <occluded>0</occluded>
        <difficult>0</difficult>
        <bndbox>
            <xmin>308</xmin>
            <ymin>97</ymin>
            <xmax>359</xmax>
            <ymax>249</ymax>
        </bndbox>
    </object>
    <object>
        <name>Tomato leaf yellow virus</name>
        <pose>Unspecified</pose>
        <truncated>0</truncated>
        <occluded>0</occluded>
        <difficult>0</difficult>
        <bndbox>
            <xmin>228</xmin>
            <ymin>112</ymin>
            <xmax>258</xmax>
            <ymax>172</ymax>
        </bndbox>
    </object>
    <object>
        <name>Tomato leaf yellow virus</name>
        <pose>Unspecified</pose>
        <truncated>0</truncated>
        <occluded>0</occluded>
        <difficult>0</difficult>
        <bndbox>
            <xmin>161</xmin>
            <ymin>229</ymin>
            <xmax>201</xmax>
            <ymax>264</ymax>
        </bndbox>
    </object>
    <object>
        <name>Tomato leaf yellow virus</name>
        <pose>Unspecified</pose>
        <truncated>0</truncated>
        <occluded>0</occluded>
        <difficult>0</difficult>
        <bndbox>
            <xmin>143</xmin>
            <ymin>187</ymin>
            <xmax>184</xmax>
            <ymax>240</ymax>
        </bndbox>
    </object>
    <object>
        <name>Tomato leaf yellow virus</name>
        <pose>Unspecified</pose>
        <truncated>0</truncated>
        <occluded>0</occluded>
        <difficult>0</difficult>
        <bndbox>
            <xmin>206</xmin>
            <ymin>174</ymin>
            <xmax>258</xmax>
            <ymax>223</ymax>
        </bndbox>
    </object>
</annotation>